docs/Makefile
docs/__init__.py
docs/authors.rst
docs/conf.py
docs/contributing.rst
docs/history.rst
docs/index.rst
docs/installation.rst
docs/make.bat
docs/readme.rst
docs/usage.rst
wpc/__init__.py
wpc/shell_cli.py
wpc/boot/__init__.py
wpc/boot/boot.py
wpc/cli/__init__.py
wpc/cli/config_cmd.py
wpc/cli/customer_cmd.py
wpc/cli/invoice_cmd.py
wpc/cli/payment_cmd.py
wpc/cli/report_cmd.py
wpc/cli/shell.py
wpc/cli/work_cmd.py
wpc/config/__init__.py
wpc/config/config.py
wpc/db/__init__.py
wpc/db/db.py
wpc/db/query.py
wpc/doc/__init__.py
wpc/doc/doc.py
wpc/doc/doc_html.py
wpc/doc/doc_tex.py
wpc/doc/invoice.py
wpc/doc/registry.py
wpc/model/__init__.py
wpc/model/base.py
wpc/model/client.py
wpc/model/customer.py
wpc/model/invoice.py
wpc/model/invoice_with_hours.py
wpc/model/payment.py
wpc/model/report.py
wpc/model/work.py
wpc/repository/__init__.py
wpc/repository/baserepo.py
wpc/repository/crudrepo.py
wpc/repository/customer_repo.py
wpc/repository/invoice_repo.py
wpc/repository/payment_repo.py
wpc/repository/repo.py
wpc/repository/report_repo.py
wpc/repository/workrepo.py
wpc-0.2.1.dist-info/AUTHORS.rst
wpc-0.2.1.dist-info/LICENSE
wpc-0.2.1.dist-info/METADATA
wpc-0.2.1.dist-info/WHEEL
wpc-0.2.1.dist-info/entry_points.txt
wpc-0.2.1.dist-info/top_level.txt
wpc-0.2.1.dist-info/RECORD
