Metadata-Version: 2.1
Name: wpc
Version: 0.2.1
Summary: WPC is a light-weight, highly configurable and easy to use library with a minimal CLI, with the objective of manage your work (hours and costs) and emit invoices.
Home-page: https://github.com/lparolari/wpc
Author: Luca Parolari
Author-email: luca.parolari23@gmail.com
License: GNU General Public License v3
Keywords: wpc
Platform: UNKNOWN
Classifier: Development Status :: 2 - Pre-Alpha
Classifier: Intended Audience :: Developers
Classifier: License :: OSI Approved :: GNU General Public License v3 (GPLv3)
Classifier: Natural Language :: English
Classifier: Programming Language :: Python :: 3
Classifier: Programming Language :: Python :: 3.4
Classifier: Programming Language :: Python :: 3.5
Classifier: Programming Language :: Python :: 3.6
Classifier: Programming Language :: Python :: 3.7
Requires-Dist: Click (>=6.0)
Requires-Dist: configparser
Requires-Dist: num2words
Requires-Dist: pylatex
Requires-Dist: python-dateutil
Requires-Dist: sqlalchemy
Requires-Dist: tabulate
